{
  "version": 6,
  "entities": [
    {
      "entity": {
        "type": "Project",
        "id": "09ebbb5c-4fa6-4248-ac42-8d770eb83d2a",
        "name": "Keluarga Berencana"
      },
      "children": [
        {
          "entity": {
            "type": "Service",
            "id": "74e2e340-655d-46c1-9c33-4a771b168781",
            "name": "kontrasepsi"
          },
          "children": [
            {
              "entity": {
                "type": "Request",
                "method": {
                  "requestBody": true,
                  "link": "http://tools.ietf.org/html/rfc7231#section-4.3.3",
                  "name": "POST"
                },
                "body": {
                  "formBody": {
                    "overrideContentType": true,
                    "encoding": "application/x-www-form-urlencoded",
                    "items": []
                  },
                  "bodyType": "Text",
                  "textBody": "{\n  \"name\" : \"Kondom Junior\" \n}"
                },
                "uri": {
                  "query": {
                    "delimiter": "&",
                    "items": []
                  },
                  "scheme": {
                    "name": "http",
                    "version": "V11"
                  },
                  "host": "localhost:8080",
                  "path": "/kontrasepsi"
                },
                "id": "d0cdbfdc-89c0-438a-a4bc-2287adf5aa5c",
                "name": "Add Kontrasepsi",
                "headers": [
                  {
                    "enabled": true,
                    "name": "Content-Type",
                    "value": "application/json"
                  }
                ]
              }
            },
            {
              "entity": {
                "type": "Request",
                "method": {
                  "requestBody": true,
                  "link": "http://tools.ietf.org/html/rfc7231#section-4.3.4",
                  "name": "PUT"
                },
                "body": {
                  "formBody": {
                    "overrideContentType": true,
                    "encoding": "application/x-www-form-urlencoded",
                    "items": []
                  },
                  "bodyType": "Text",
                  "textBody": "{\n  \"name\" : \"Silikon\"\n}"
                },
                "uri": {
                  "query": {
                    "delimiter": "&",
                    "items": []
                  },
                  "scheme": {
                    "name": "http",
                    "version": "V11"
                  },
                  "host": "localhost:8080",
                  "path": "/kontrasepsi/2"
                },
                "id": "e490c25f-a71b-4730-a274-20b58f2607c9",
                "name": "Edit Kontrasepsi",
                "headers": [
                  {
                    "enabled": true,
                    "name": "Content-Type",
                    "value": "application/json"
                  }
                ]
              }
            },
            {
              "entity": {
                "type": "Request",
                "method": {
                  "link": "http://tools.ietf.org/html/rfc7231#section-4.3.1",
                  "name": "GET"
                },
                "body": {
                  "formBody": {
                    "overrideContentType": true,
                    "encoding": "application/x-www-form-urlencoded",
                    "items": []
                  },
                  "bodyType": "Text"
                },
                "uri": {
                  "query": {
                    "delimiter": "&",
                    "items": []
                  },
                  "scheme": {
                    "name": "http",
                    "version": "V11"
                  },
                  "host": "localhost:8080",
                  "path": "/kontrasepsi/4"
                },
                "id": "a439503a-347c-4b34-8c75-33d7a7fed7ff",
                "name": "Find Kontrasepsi",
                "headers": []
              }
            },
            {
              "entity": {
                "type": "Request",
                "method": {
                  "link": "http://tools.ietf.org/html/rfc7231#section-4.3.1",
                  "name": "GET"
                },
                "body": {
                  "formBody": {
                    "overrideContentType": true,
                    "encoding": "application/x-www-form-urlencoded",
                    "items": []
                  },
                  "bodyType": "Text"
                },
                "uri": {
                  "query": {
                    "delimiter": "&",
                    "items": []
                  },
                  "scheme": {
                    "name": "http",
                    "version": "V11"
                  },
                  "host": "localhost:8080",
                  "path": "/kontrasepsi"
                },
                "id": "bfd2f62d-3c10-4755-bb99-b0e595a10e68",
                "name": "Find Kontrasepsis",
                "headers": []
              }
            },
            {
              "entity": {
                "type": "Request",
                "method": {
                  "link": "http://tools.ietf.org/html/rfc7231#section-4.3.5",
                  "name": "DELETE"
                },
                "body": {
                  "formBody": {
                    "overrideContentType": true,
                    "encoding": "application/x-www-form-urlencoded",
                    "items": []
                  },
                  "bodyType": "Text"
                },
                "uri": {
                  "query": {
                    "delimiter": "&",
                    "items": []
                  },
                  "scheme": {
                    "name": "http",
                    "version": "V11"
                  },
                  "host": "localhost:8080",
                  "path": "/kontrasepsi/4"
                },
                "id": "ae8ad63e-9a64-4b0a-9728-435516c439ac",
                "name": "Remove Kontrasepsi",
                "headers": []
              }
            }
          ]
        },
        {
          "entity": {
            "type": "Service",
            "id": "02854bb4-4a41-4e66-8e55-b89e65906efb",
            "name": "pemakaikontrasepsi"
          },
          "children": [
            {
              "entity": {
                "type": "Request",
                "method": {
                  "requestBody": true,
                  "link": "http://tools.ietf.org/html/rfc7231#section-4.3.3",
                  "name": "POST"
                },
                "body": {
                  "formBody": {
                    "overrideContentType": true,
                    "encoding": "application/x-www-form-urlencoded",
                    "items": []
                  },
                  "bodyType": "Text",
                  "textBody": "{\n  \"propinsi\" : {\"id\" : 8},\n  \"jumlahPemakai\" : 200,\n  \"kontrasepsi\" : {\"id\" : 3}\n}"
                },
                "uri": {
                  "query": {
                    "delimiter": "&",
                    "items": []
                  },
                  "scheme": {
                    "name": "http",
                    "version": "V11"
                  },
                  "host": "localhost:8080",
                  "path": "/pemakaikontrasepsi"
                },
                "id": "e03f2d19-c4ba-45b9-b5b3-441935c2b86f",
                "name": "Add PemakaiKontrasepsi",
                "headers": [
                  {
                    "enabled": true,
                    "name": "Content-Type",
                    "value": "application/json"
                  }
                ]
              }
            },
            {
              "entity": {
                "type": "Request",
                "method": {
                  "requestBody": true,
                  "link": "http://tools.ietf.org/html/rfc7231#section-4.3.4",
                  "name": "PUT"
                },
                "body": {
                  "formBody": {
                    "overrideContentType": true,
                    "encoding": "application/x-www-form-urlencoded",
                    "items": []
                  },
                  "bodyType": "Text",
                  "textBody": "{\n  \"propinsi\" : {\"id\" : 8},\n  \"jumlahPemakai\" : 100,\n  \"kontrasepsi\" : {\"id\" : 3}\n}"
                },
                "uri": {
                  "query": {
                    "delimiter": "&",
                    "items": []
                  },
                  "scheme": {
                    "name": "http",
                    "version": "V11"
                  },
                  "host": "localhost:8080",
                  "path": "/pemakaikontrasepsi/1"
                },
                "id": "d621d059-d237-4a95-bef6-e55ef6d701ae",
                "name": "Edit PemakaiKontrasepsi",
                "headers": [
                  {
                    "enabled": true,
                    "name": "Content-Type",
                    "value": "application/json"
                  }
                ]
              }
            },
            {
              "entity": {
                "type": "Request",
                "method": {
                  "link": "http://tools.ietf.org/html/rfc7231#section-4.3.1",
                  "name": "GET"
                },
                "body": {
                  "formBody": {
                    "overrideContentType": true,
                    "encoding": "application/x-www-form-urlencoded",
                    "items": []
                  },
                  "bodyType": "Text"
                },
                "uri": {
                  "query": {
                    "delimiter": "&",
                    "items": []
                  },
                  "scheme": {
                    "name": "http",
                    "version": "V11"
                  },
                  "host": "localhost:8080",
                  "path": "/pemakaikontrasepsi/2"
                },
                "id": "09662497-6b88-4a0d-9034-09f54e605385",
                "name": "Find PemakaiKontrasepsi",
                "headers": []
              }
            },
            {
              "entity": {
                "type": "Request",
                "method": {
                  "link": "http://tools.ietf.org/html/rfc7231#section-4.3.1",
                  "name": "GET"
                },
                "body": {
                  "formBody": {
                    "overrideContentType": true,
                    "encoding": "application/x-www-form-urlencoded",
                    "items": []
                  },
                  "bodyType": "Text"
                },
                "uri": {
                  "query": {
                    "delimiter": "&",
                    "items": []
                  },
                  "scheme": {
                    "name": "http",
                    "version": "V11"
                  },
                  "host": "localhost:8080",
                  "path": "/pemakaikontrasepsi"
                },
                "id": "e8b5e585-d7e3-48b9-b093-bbefd9208f5d",
                "name": "Find PemakaiKontrasepsis",
                "headers": []
              }
            },
            {
              "entity": {
                "type": "Request",
                "method": {
                  "link": "http://tools.ietf.org/html/rfc7231#section-4.3.5",
                  "name": "DELETE"
                },
                "body": {
                  "formBody": {
                    "overrideContentType": true,
                    "encoding": "application/x-www-form-urlencoded",
                    "items": []
                  },
                  "bodyType": "Text"
                },
                "uri": {
                  "query": {
                    "delimiter": "&",
                    "items": []
                  },
                  "scheme": {
                    "name": "http",
                    "version": "V11"
                  },
                  "host": "localhost:8080",
                  "path": "/pemakaikontrasepsi/11"
                },
                "id": "98d0976b-529b-4824-8a36-4a3ea2b763a4",
                "name": "Remove PemakaiKontrasepsi",
                "headers": []
              }
            }
          ]
        },
        {
          "entity": {
            "type": "Service",
            "description": "",
            "id": "ae87a66b-cae6-4158-9e92-f337327981c0",
            "name": "propinsi"
          },
          "children": [
            {
              "entity": {
                "type": "Request",
                "method": {
                  "requestBody": true,
                  "link": "http://tools.ietf.org/html/rfc7231#section-4.3.3",
                  "name": "POST"
                },
                "body": {
                  "formBody": {
                    "overrideContentType": true,
                    "encoding": "application/x-www-form-urlencoded",
                    "items": []
                  },
                  "bodyType": "Text",
                  "textBody": "{\n  \"name\" : \"Bali\"\n}"
                },
                "uri": {
                  "query": {
                    "delimiter": "&",
                    "items": []
                  },
                  "scheme": {
                    "name": "http",
                    "version": "V11"
                  },
                  "host": "localhost:8080",
                  "path": "/propinsi"
                },
                "id": "e183028d-b084-488a-814f-3d6504c7d97b",
                "name": "Add Propinsi",
                "headers": [
                  {
                    "enabled": true,
                    "name": "Content-Type",
                    "value": "application/json"
                  }
                ]
              }
            },
            {
              "entity": {
                "type": "Request",
                "method": {
                  "requestBody": true,
                  "link": "http://tools.ietf.org/html/rfc7231#section-4.3.4",
                  "name": "PUT"
                },
                "body": {
                  "formBody": {
                    "overrideContentType": true,
                    "encoding": "application/x-www-form-urlencoded",
                    "items": []
                  },
                  "bodyType": "Text",
                  "textBody": "{\n  \"name\" : \"Papua\"\n}"
                },
                "uri": {
                  "query": {
                    "delimiter": "&",
                    "items": []
                  },
                  "scheme": {
                    "name": "http",
                    "version": "V11"
                  },
                  "host": "localhost:8080",
                  "path": "/propinsi/1"
                },
                "id": "185c7639-1f8c-4af0-b925-9476905def0a",
                "name": "Edit Propinsi",
                "headers": [
                  {
                    "enabled": true,
                    "name": "Content-Type",
                    "value": "application/json"
                  }
                ]
              }
            },
            {
              "entity": {
                "type": "Request",
                "method": {
                  "link": "http://tools.ietf.org/html/rfc7231#section-4.3.1",
                  "name": "GET"
                },
                "body": {
                  "formBody": {
                    "overrideContentType": true,
                    "encoding": "application/x-www-form-urlencoded",
                    "items": []
                  },
                  "bodyType": "Text"
                },
                "uri": {
                  "query": {
                    "delimiter": "&",
                    "items": []
                  },
                  "scheme": {
                    "name": "http",
                    "version": "V11"
                  },
                  "host": "localhost:8080",
                  "path": "/propinsi/1"
                },
                "id": "725baae5-8d8a-4706-b9f3-e2036d95a480",
                "name": "Find Propinsi",
                "headers": []
              }
            },
            {
              "entity": {
                "type": "Request",
                "method": {
                  "link": "http://tools.ietf.org/html/rfc7231#section-4.3.1",
                  "name": "GET"
                },
                "body": {
                  "formBody": {
                    "overrideContentType": true,
                    "encoding": "application/x-www-form-urlencoded",
                    "items": []
                  },
                  "bodyType": "Text"
                },
                "uri": {
                  "query": {
                    "delimiter": "&",
                    "items": []
                  },
                  "scheme": {
                    "name": "http",
                    "version": "V11"
                  },
                  "host": "localhost:8080",
                  "path": "/propinsi"
                },
                "id": "b88d153c-0db0-47e3-9821-627a375c3a15",
                "name": "Find Propinsis",
                "headers": []
              }
            },
            {
              "entity": {
                "type": "Request",
                "method": {
                  "link": "http://tools.ietf.org/html/rfc7231#section-4.3.5",
                  "name": "DELETE"
                },
                "body": {
                  "formBody": {
                    "overrideContentType": true,
                    "encoding": "application/x-www-form-urlencoded",
                    "items": []
                  },
                  "bodyType": "Text"
                },
                "uri": {
                  "query": {
                    "delimiter": "&",
                    "items": []
                  },
                  "scheme": {
                    "name": "http",
                    "version": "V11"
                  },
                  "host": "localhost:8080",
                  "path": "/propinsi/10"
                },
                "id": "175f0c84-a049-42cd-bc5b-f0361f57541e",
                "name": "Remove Propinsi",
                "headers": []
              }
            }
          ]
        }
      ]
    }
  ]
}